MRI_PulseSim/MRI_PulseSim_final.py
MRI_PulseSim/__init__.py
MRI_PulseSim-0.0.2.dist-info/LICENSE.txt
MRI_PulseSim-0.0.2.dist-info/METADATA
MRI_PulseSim-0.0.2.dist-info/WHEEL
MRI_PulseSim-0.0.2.dist-info/top_level.txt
MRI_PulseSim-0.0.2.dist-info/RECORD
