Metadata-Version: 2.1
Name: MRI-PulseSim
Version: 0.0.2
Summary: Description of your Python package
Home-page: https://github.com/totensen/MRI_PulseSim
Author: Ties Tensen
Author-email: ties.tensen@gmail.com
License: UNKNOWN
Platform: UNKNOWN
Classifier: Programming Language :: Python :: 3
Classifier: License :: OSI Approved :: MIT License
Classifier: Operating System :: OS Independent
Requires-Python: >=3.6
License-File: LICENSE.txt
